djangocms_layouttools/__init__.py
djangocms_layouttools/admin.py
djangocms_layouttools/apps.py
djangocms_layouttools/cms_plugins.py
djangocms_layouttools/fields.py
djangocms_layouttools/models.py
djangocms_layouttools/views.py
djangocms_layouttools/migrations/0001_initial.py
djangocms_layouttools/migrations/__init__.py
djangocms_layouttools/templates/djangocms_layouttools/section.html
djangocms_layouttools/tests/__init__.py
djangocms_layouttools/tests/settings.py
djangocms_layouttools/tests/tests_models.py
djangocms_layouttools-0.1.4.dist-info/LICENSE.txt
djangocms_layouttools-0.1.4.dist-info/METADATA
djangocms_layouttools-0.1.4.dist-info/WHEEL
djangocms_layouttools-0.1.4.dist-info/top_level.txt
djangocms_layouttools-0.1.4.dist-info/RECORD
