Metadata-Version: 2.1
Name: djangocms-layouttools
Version: 0.1.4
Summary: Adds layout Section and other plugins to django CMS.
Home-page: https://github.com/mci/djangocms-layouttools
Author: Russell Moffitt, Marine Conservation Institute
Author-email: Russell.Moffitt@marine-conservation.org
License: MIT
Classifier: Development Status :: 4 - Beta
Classifier: Environment :: Web Environment
Classifier: Framework :: Django
Classifier: Intended Audience :: Developers
Classifier: License :: OSI Approved :: BSD License
Classifier: Operating System :: OS Independent
Classifier: Programming Language :: Python
Classifier: Programming Language :: Python :: 2
Classifier: Programming Language :: Python :: 2.7
Classifier: Programming Language :: Python :: 3
Classifier: Programming Language :: Python :: 3.4
Classifier: Programming Language :: Python :: 3.5
Classifier: Programming Language :: Python :: 3.6
Classifier: Programming Language :: Python :: 3.7
Classifier: Programming Language :: Python :: 3.9
Classifier: Topic :: Internet :: WWW/HTTP
Classifier: Topic :: Internet :: WWW/HTTP :: Dynamic Content
Classifier: Topic :: Software Development :: Libraries :: Application Frameworks
Classifier: Topic :: Software Development :: Libraries :: Python Modules
License-File: LICENSE.txt
Requires-Dist: django-cms (>=3.3.1)
Requires-Dist: django-filer (>=1.2.4)
Requires-Dist: djangocms-attributes-field (>=0.1.1)
